aipha_geo_solutions/AIPHAProcessing.py
aipha_geo_solutions/__init__.py
aipha_geo_solutions/operators.py
aipha_geo_solutions/webservice_api.py
aipha_geo_solutions-0.9.31.dist-info/METADATA
aipha_geo_solutions-0.9.31.dist-info/WHEEL
aipha_geo_solutions-0.9.31.dist-info/licenses/LICENSE
aipha_geo_solutions-0.9.31.dist-info/RECORD
