Metadata-Version: 2.4
Name: aipha_geo_solutions
Version: 0.9.31
Summary: A python API to the AIPHA webservices
Project-URL: Homepage, https://github.com/AIPHA-Geo-Solutions/
Project-URL: Bug Tracker, https://github.com/AIPHA-Geo-Solutions/AIPHAPythonAPI/issues
Author-email: Timo Hackel <timo.hackel@aipha.ch>
License-File: LICENSE
Classifier: License :: OSI Approved :: MIT License
Classifier: Operating System :: OS Independent
Classifier: Programming Language :: Python :: 3
Requires-Python: >=3.8
